setup.py
flowzillow/__init__.py
flowzillow/client.py
flowzillow/constants.py
flowzillow/exceptions.py
flowzillow.egg-info/PKG-INFO
flowzillow.egg-info/SOURCES.txt
flowzillow.egg-info/dependency_links.txt
flowzillow.egg-info/requires.txt
flowzillow.egg-info/top_level.txt