Metadata-Version: 1.0
Name: flowzillow
Version: 0.1.3
Summary: An intuitive python wrapper around the Zillow API. Includes support for the undocumented search API
Home-page: UNKNOWN
Author: Gregory Rehm
Author-email: UNKNOWN
License: UNKNOWN
Platform: UNKNOWN
